hubble_futures/__init__.py
hubble_futures/aster.py
hubble_futures/base.py
hubble_futures/config.py
hubble_futures/function_log.py
hubble_futures/version.py
hubble_futures/weex.py
hubble_futures-0.2.11.dist-info/METADATA
hubble_futures-0.2.11.dist-info/WHEEL
hubble_futures-0.2.11.dist-info/licenses/LICENSE
hubble_futures-0.2.11.dist-info/RECORD
