Metadata-Version: 2.4
Name: hubble-futures
Version: 0.2.11
Summary: Unified futures exchange client library for Hubble trading platform
Project-URL: Homepage, https://github.com/hubble-ecosystem/hubble-futures
Project-URL: Repository, https://github.com/hubble-ecosystem/hubble-futures
Project-URL: Documentation, https://github.com/hubble-ecosystem/hubble-futures/blob/main/README.md
Project-URL: Bug Tracker, https://github.com/hubble-ecosystem/hubble-futures/issues
Author-email: Hubble Team <dev@hubble.com>
License: MIT
License-File: LICENSE
Keywords: api,aster,binance,cryptocurrency,exchange,futures,trading,weex
Classifier: Development Status :: 3 - Alpha
Classifier: Intended Audience :: Developers
Classifier: License :: OSI Approved :: MIT License
Classifier: Programming Language :: Python :: 3
Classifier: Programming Language :: Python :: 3.10
Classifier: Programming Language :: Python :: 3.11
Classifier: Programming Language :: Python :: 3.12
Classifier: Topic :: Office/Business :: Financial
Classifier: Topic :: Software Development :: Libraries :: Python Modules
Requires-Python: >=3.10
Requires-Dist: loguru>=0.7.0
Requires-Dist: requests>=2.28.0
Provides-Extra: dev
Requires-Dist: mypy>=1.0; extra == 'dev'
Requires-Dist: pytest-cov>=4.0; extra == 'dev'
Requires-Dist: pytest-mock>=3.10; extra == 'dev'
Requires-Dist: pytest>=7.0; extra == 'dev'
Requires-Dist: python-dotenv>=1.0.0; extra == 'dev'
Requires-Dist: responses>=0.23.0; extra == 'dev'
Requires-Dist: ruff>=0.1.0; extra == 'dev'
Requires-Dist: types-requests>=2.28.0; extra == 'dev'
